{
  "tool": "khr-linux-agent",
  "version": "0.0.1-sprint9",
  "mode": "dry-run",
  "resourceLeaseDryRun": {
    "allowed": false,
    "blocked": true,
    "reason": "ResourcePort does not allow envelope for requested resource",
    "rollbackPlan": [
      "revert cgroup cpu.max/memory.max to prior values captured pre-apply"
    ],
    "verificationPlan": [
      "read back cgroup limits",
      "compare cgroup.events pressure",
      "confirm process RSS/CPU throttle metrics"
    ],
    "resourcePortCheck": "incompatible"
  },
  "cgroupEnvelopePlan": {
    "cgroupVersion": "v2",
    "wouldWrite": false
  },
  "mutationsForbidden": true,
  "unsafeApplyFlagPresent": false,
  "futureApplyGateRequired": false
}
