{"$schema":"https://json-schema.org/draft/2020-12/schema","title":"controller-smoke-tick-generated-action-v1","type":"object","required":["actionId","donorShellId","receiverShellId","resource","amount","executionScopeRecommendation","productionScope","productionCanaryScope","sandboxNonprodScope","operatorControlledScope","expectedMovedIdleValue","expectedCompressionGain","generalProductionAutoAllowed","productionAutoWithPolicy","selectedForExecution","executionBlocked","blockerCodes","evidenceRefs","claimBoundary"],"properties":{"executionScopeRecommendation":{"enum":["operator_controlled","sandbox_auto_eligible","nonprod_auto_eligible","production_canary_eligible","remediation_only","blocked"]}}}
