{
  "$schema": "https://json-schema.org/draft/2020-12/schema",
  "$id": "https://github.com/marco-simoncini/Karl-Hyperdensity/schemas/operator-apply-gate-v1.schema.json",
  "title": "KARL Hyperdensity Operator Apply Gate v1",
  "type": "object",
  "required": ["milestone", "surfaceVersion", "gateId", "sourceActionSlateRef", "sourceActionId", "sourceLeaseCandidateId", "state", "mutationScope", "productionScope", "operatorControlledApplyAllowed", "autoApplyAllowed", "productionAutonomousApplyAllowed", "rawRuntimeControlsExposed", "operatorApprovalRequired", "safetyInvariants", "claimPolicyRef", "sourceOfTruth", "claimBoundaries"],
  "properties": {
    "milestone": { "const": "hyperdensity_operator_controlled_apply_gate_v1" },
    "surfaceVersion": { "type": "string" },
    "gateId": { "type": "string" },
    "sourceActionSlateRef": { "type": "string" },
    "sourceActionId": { "type": "string" },
    "sourceLeaseCandidateId": { "type": "string" },
    "state": { "type": "string" },
    "mutationScope": { "type": "string" },
    "productionScope": { "const": false },
    "operatorControlledApplyAllowed": { "const": true },
    "autoApplyAllowed": { "const": false },
    "productionAutonomousApplyAllowed": { "const": false },
    "rawRuntimeControlsExposed": { "const": false },
    "operatorApprovalRequired": { "type": "boolean" },
    "operatorApprovalRef": { "type": "string" },
    "applyRequestRef": { "type": "string" },
    "fluidvirtInvocationRef": { "type": "string" },
    "mutationObservationRef": { "type": "string" },
    "postVerifyRef": { "type": "string" },
    "rollbackWindowRef": { "type": "string" },
    "auditEventRefs": { "type": "array", "items": { "type": "string" } },
    "safetyInvariants": { "type": "object" },
    "claimPolicyRef": { "type": "string" },
    "sourceOfTruth": { "type": "object" },
    "claimBoundaries": { "type": "array", "items": { "type": "string" } },
    "blockers": { "type": "array", "items": { "type": "string" } }
  }
}
